{
  "kind": "Listing",
  "data": {
    "modhash": "dzu35njokv2cc2c6c047c84fc92abfefb7f397272204493c1c",
    "children": [
      {
        "kind": "t1",
        "data": {
          "subreddit_id": "t5_2to41",
          "link_title": "TIFU by stripping for my doctor",
          "banned_by": null,
          "removal_reason": null,
          "link_id": "t3_4c7398",
          "link_author": "Sunnybunny9",
          "likes": true,
          "replies": "",
          "user_reports": [

          ],
          "saved": false,
          "id": "d1ftpuy",
          "gilded": 0,
          "archived": false,
          "stickied": false,
          "author": "damien5314",
          "parent_id": "t1_d1fr9vy",
          "score": 47,
          "approved_by": null,
          "over_18": true,
          "report_reasons": null,
          "controversiality": 0,
          "body": "They usually give you a robe to wear that ties around the back from my experiences. His lack of undergarments might have only been seen when walking across the room ;)",
          "edited": false,
          "author_flair_css_class": null,
          "downs": 0,
          "body_html": "&lt;div class=\"md\"&gt;&lt;p&gt;They usually give you a robe to wear that ties around the back from my experiences. His lack of undergarments might have only been seen when walking across the room ;)&lt;\/p&gt;\n&lt;\/div&gt;",
          "quarantine": false,
          "subreddit": "tifu",
          "score_hidden": false,
          "name": "t1_d1ftpuy",
          "created": 1459155691,
          "author_flair_text": null,
          "link_url": "https:\/\/www.reddit.com\/r\/tifu\/comments\/4c7398\/tifu_by_stripping_for_my_doctor\/",
          "created_utc": 1459126891,
          "ups": 47,
          "mod_reports": [

          ],
          "num_reports": null,
          "distinguished": null
        }
      },
      {
        "kind": "t1",
        "data": {
          "subreddit_id": "t5_2qizd",
          "link_title": "Accessing the API with logged out users",
          "banned_by": null,
          "removal_reason": null,
          "link_id": "t3_4b3fnx",
          "link_author": "JMCoo",
          "likes": true,
          "replies": "",
          "user_reports": [

          ],
          "saved": false,
          "id": "d15u1qh",
          "gilded": 0,
          "archived": false,
          "stickied": false,
          "author": "damien5314",
          "parent_id": "t1_d15t7qm",
          "score": 1,
          "approved_by": null,
          "over_18": false,
          "report_reasons": null,
          "controversiality": 0,
          "body": "I believe the flow that is being deprecated is authenticated access via cookie for apps that are still taking username\/password and logging into reddit that way. But I'm not sure how that works and haven't been following that news since I decided to go the OAuth route from the beginning.",
          "edited": false,
          "author_flair_css_class": null,
          "downs": 0,
          "body_html": "&lt;div class=\"md\"&gt;&lt;p&gt;I believe the flow that is being deprecated is authenticated access via cookie for apps that are still taking username\/password and logging into reddit that way. But I&amp;#39;m not sure how that works and haven&amp;#39;t been following that news since I decided to go the OAuth route from the beginning.&lt;\/p&gt;\n&lt;\/div&gt;",
          "quarantine": false,
          "subreddit": "redditdev",
          "score_hidden": false,
          "name": "t1_d15u1qh",
          "created": 1458437476,
          "author_flair_text": null,
          "link_url": "https:\/\/www.reddit.com\/r\/redditdev\/comments\/4b3fnx\/accessing_the_api_with_logged_out_users\/",
          "created_utc": 1458408676,
          "ups": 1,
          "mod_reports": [

          ],
          "num_reports": null,
          "distinguished": null
        }
      },
      {
        "kind": "t1",
        "data": {
          "subreddit_id": "t5_2qizd",
          "link_title": "Accessing the API with logged out users",
          "banned_by": null,
          "removal_reason": null,
          "link_id": "t3_4b3fnx",
          "link_author": "JMCoo",
          "likes": true,
          "replies": "",
          "user_reports": [

          ],
          "saved": false,
          "id": "d15szwv",
          "gilded": 0,
          "archived": false,
          "stickied": false,
          "author": "damien5314",
          "parent_id": "t1_d15r5iz",
          "score": 1,
          "approved_by": null,
          "over_18": false,
          "report_reasons": null,
          "controversiality": 0,
          "body": "The app-only oauth token still expires, you just need to request a new one every hour.\n\nI think appending `.json` to your requests will keep working for the calls you're using it for, just the same as if you had entered it into a browser. But not all endpoints are accessible that way, so I would just implement the OAuth flow and put your mind at rest knowing you're using the proper method.",
          "edited": false,
          "author_flair_css_class": null,
          "downs": 0,
          "body_html": "&lt;div class=\"md\"&gt;&lt;p&gt;The app-only oauth token still expires, you just need to request a new one every hour.&lt;\/p&gt;\n\n&lt;p&gt;I think appending &lt;code&gt;.json&lt;\/code&gt; to your requests will keep working for the calls you&amp;#39;re using it for, just the same as if you had entered it into a browser. But not all endpoints are accessible that way, so I would just implement the OAuth flow and put your mind at rest knowing you&amp;#39;re using the proper method.&lt;\/p&gt;\n&lt;\/div&gt;",
          "quarantine": false,
          "subreddit": "redditdev",
          "score_hidden": false,
          "name": "t1_d15szwv",
          "created": 1458435614,
          "author_flair_text": null,
          "link_url": "https:\/\/www.reddit.com\/r\/redditdev\/comments\/4b3fnx\/accessing_the_api_with_logged_out_users\/",
          "created_utc": 1458406814,
          "ups": 1,
          "mod_reports": [

          ],
          "num_reports": null,
          "distinguished": null
        }
      },
      {
        "kind": "t1",
        "data": {
          "subreddit_id": "t5_2qizd",
          "link_title": "Accessing the API with logged out users",
          "banned_by": null,
          "removal_reason": null,
          "link_id": "t3_4b3fnx",
          "link_author": "JMCoo",
          "likes": true,
          "replies": "",
          "user_reports": [

          ],
          "saved": false,
          "id": "d15qo1w",
          "gilded": 0,
          "archived": false,
          "stickied": false,
          "author": "damien5314",
          "parent_id": "t3_4b3fnx",
          "score": 2,
          "approved_by": null,
          "over_18": false,
          "report_reasons": null,
          "controversiality": 0,
          "body": "You can retrieve a token for your application just as you can retrieve a token for users. In my app I retrieve an app token by default until users sign in, then use their auth token instead.\n\nhttps:\/\/github.com\/reddit\/reddit\/wiki\/OAuth2#application-only-oauth",
          "edited": false,
          "author_flair_css_class": null,
          "downs": 0,
          "body_html": "&lt;div class=\"md\"&gt;&lt;p&gt;You can retrieve a token for your application just as you can retrieve a token for users. In my app I retrieve an app token by default until users sign in, then use their auth token instead.&lt;\/p&gt;\n\n&lt;p&gt;&lt;a href=\"https:\/\/github.com\/reddit\/reddit\/wiki\/OAuth2#application-only-oauth\"&gt;https:\/\/github.com\/reddit\/reddit\/wiki\/OAuth2#application-only-oauth&lt;\/a&gt;&lt;\/p&gt;\n&lt;\/div&gt;",
          "quarantine": false,
          "subreddit": "redditdev",
          "score_hidden": false,
          "name": "t1_d15qo1w",
          "created": 1458431316,
          "author_flair_text": null,
          "link_url": "https:\/\/www.reddit.com\/r\/redditdev\/comments\/4b3fnx\/accessing_the_api_with_logged_out_users\/",
          "created_utc": 1458402516,
          "ups": 2,
          "mod_reports": [

          ],
          "num_reports": null,
          "distinguished": null
        }
      },
      {
        "kind": "t1",
        "data": {
          "subreddit_id": "t5_2qizd",
          "link_title": "Does the world need another reddit app for android?",
          "banned_by": null,
          "removal_reason": null,
          "link_id": "t3_49lifu",
          "link_author": "rms_returns",
          "likes": true,
          "replies": "",
          "user_reports": [

          ],
          "saved": false,
          "id": "d12s3em",
          "gilded": 0,
          "archived": false,
          "stickied": false,
          "author": "damien5314",
          "parent_id": "t1_d0tej0i",
          "score": 1,
          "approved_by": null,
          "over_18": false,
          "report_reasons": null,
          "controversiality": 0,
          "body": "Write a generic reddit client if you want. I did the same thing for learning Android, and have been working on the app for a year now. It has no features missing from other reddit apps, and frankly I couldn't care less. It doesn't need to turn into anything big. \n\nNo one should keep you from making what you want to make, just know you probably won't get many users with so much competition :P If you're okay with that, you should be fine.",
          "edited": false,
          "author_flair_css_class": null,
          "downs": 0,
          "body_html": "&lt;div class=\"md\"&gt;&lt;p&gt;Write a generic reddit client if you want. I did the same thing for learning Android, and have been working on the app for a year now. It has no features missing from other reddit apps, and frankly I couldn&amp;#39;t care less. It doesn&amp;#39;t need to turn into anything big. &lt;\/p&gt;\n\n&lt;p&gt;No one should keep you from making what you want to make, just know you probably won&amp;#39;t get many users with so much competition :P If you&amp;#39;re okay with that, you should be fine.&lt;\/p&gt;\n&lt;\/div&gt;",
          "quarantine": false,
          "subreddit": "redditdev",
          "score_hidden": false,
          "name": "t1_d12s3em",
          "created": 1458208977,
          "author_flair_text": null,
          "link_url": "https:\/\/www.reddit.com\/r\/redditdev\/comments\/49lifu\/does_the_world_need_another_reddit_app_for_android\/",
          "created_utc": 1458180177,
          "ups": 1,
          "mod_reports": [

          ],
          "num_reports": null,
          "distinguished": null
        }
      },
      {
        "kind": "t1",
        "data": {
          "subreddit_id": "t5_2qizd",
          "link_title": "Does praw respects api limit of Reddit?",
          "banned_by": null,
          "removal_reason": null,
          "link_id": "t3_4acs3s",
          "link_author": "anonuser404",
          "likes": true,
          "replies": "",
          "user_reports": [

          ],
          "saved": false,
          "id": "d12rgh8",
          "gilded": 0,
          "archived": false,
          "stickied": false,
          "author": "damien5314",
          "parent_id": "t1_d0zdpw9",
          "score": 2,
          "approved_by": null,
          "over_18": false,
          "report_reasons": null,
          "controversiality": 0,
          "body": "[Per the reddit API reference] (https:\/\/www.reddit.com\/dev\/api#GET_api_morechildren) only one request for loading comment stubs can be in flight at one time, per user. It's also generally not good to spam the API by making N concurrent requests to load every stub in a comment thread. So that's why PRAW queues the requests to be sent one by one, and that's why it takes a long time to load all comments. Honestly doubt there would be any workaround for that, considering the first point.",
          "edited": 1459318980,
          "author_flair_css_class": null,
          "downs": 0,
          "body_html": "&lt;div class=\"md\"&gt;&lt;p&gt;&lt;a href=\"https:\/\/www.reddit.com\/dev\/api#GET_api_morechildren\"&gt;Per the reddit API reference&lt;\/a&gt; only one request for loading comment stubs can be in flight at one time, per user. It&amp;#39;s also generally not good to spam the API by making N concurrent requests to load every stub in a comment thread. So that&amp;#39;s why PRAW queues the requests to be sent one by one, and that&amp;#39;s why it takes a long time to load all comments. Honestly doubt there would be any workaround for that, considering the first point.&lt;\/p&gt;\n&lt;\/div&gt;",
          "quarantine": false,
          "subreddit": "redditdev",
          "score_hidden": false,
          "name": "t1_d12rgh8",
          "created": 1458207901,
          "author_flair_text": null,
          "link_url": "https:\/\/www.reddit.com\/r\/redditdev\/comments\/4acs3s\/does_praw_respects_api_limit_of_reddit\/",
          "created_utc": 1458179101,
          "ups": 2,
          "mod_reports": [

          ],
          "num_reports": null,
          "distinguished": null
        }
      },
      {
        "kind": "t1",
        "data": {
          "subreddit_id": "t5_2r26y",
          "link_title": "Store Secret Key in Open Source App",
          "banned_by": null,
          "removal_reason": null,
          "link_id": "t3_4ao6f0",
          "link_author": "BHLHB3",
          "likes": true,
          "replies": "",
          "user_reports": [

          ],
          "saved": false,
          "id": "d120vs8",
          "gilded": 0,
          "archived": false,
          "stickied": false,
          "author": "damien5314",
          "parent_id": "t3_4ao6f0",
          "score": 1,
          "approved_by": null,
          "over_18": false,
          "report_reasons": null,
          "controversiality": 0,
          "body": "I typically define the keys in gradle.properties which is in version control, but I never check in the actual keys, just keep them locally. Then you can pass the key into BuildConfig through your gradle build script, or make it accessible to your app in some other way.",
          "edited": 1458157921,
          "author_flair_css_class": null,
          "downs": 0,
          "body_html": "&lt;div class=\"md\"&gt;&lt;p&gt;I typically define the keys in gradle.properties which is in version control, but I never check in the actual keys, just keep them locally. Then you can pass the key into BuildConfig through your gradle build script, or make it accessible to your app in some other way.&lt;\/p&gt;\n&lt;\/div&gt;",
          "quarantine": false,
          "subreddit": "androiddev",
          "score_hidden": false,
          "name": "t1_d120vs8",
          "created": 1458170238,
          "author_flair_text": null,
          "link_url": "https:\/\/www.reddit.com\/r\/androiddev\/comments\/4ao6f0\/store_secret_key_in_open_source_app\/",
          "created_utc": 1458141438,
          "ups": 1,
          "mod_reports": [

          ],
          "num_reports": null,
          "distinguished": null
        }
      },
      {
        "kind": "t1",
        "data": {
          "subreddit_id": "t5_2r26y",
          "link_title": "With no job and no school, how fast could you learn Android development?",
          "banned_by": null,
          "removal_reason": null,
          "link_id": "t3_49wfsl",
          "link_author": "[deleted]",
          "likes": true,
          "replies": "",
          "user_reports": [

          ],
          "saved": false,
          "id": "d0via5p",
          "gilded": 0,
          "archived": false,
          "stickied": false,
          "author": "damien5314",
          "parent_id": "t3_49wfsl",
          "score": 1,
          "approved_by": null,
          "over_18": false,
          "report_reasons": null,
          "controversiality": 0,
          "body": "Your definition of finishing is a bit subjective from dev to dev. Some people might release an app as soon as the functionality has value to users, and then iterate on it in future releases. Others will wait until they are largely feature complete and bug free before they even go into beta.\n\nI started with Android while working full time, but had a good amount of idle time on the job to work on my apps. I also had a decent amount of Java experience going in. I think it took me a few weeks to get my first app onto the store, but it was a simple app focused on a pretty small user base, so I didn't really feel the need to make it perfect for all device sizes\/configurations, or anything like that.\n\nI'd say the important thing is to start with a simple project that you think is achievable and builds largely on what you already know (if anything). If you start too big it can be overwhelming trying to connect all of the pieces, and you might not end up finishing at all.",
          "edited": false,
          "author_flair_css_class": null,
          "downs": 0,
          "body_html": "&lt;div class=\"md\"&gt;&lt;p&gt;Your definition of finishing is a bit subjective from dev to dev. Some people might release an app as soon as the functionality has value to users, and then iterate on it in future releases. Others will wait until they are largely feature complete and bug free before they even go into beta.&lt;\/p&gt;\n\n&lt;p&gt;I started with Android while working full time, but had a good amount of idle time on the job to work on my apps. I also had a decent amount of Java experience going in. I think it took me a few weeks to get my first app onto the store, but it was a simple app focused on a pretty small user base, so I didn&amp;#39;t really feel the need to make it perfect for all device sizes\/configurations, or anything like that.&lt;\/p&gt;\n\n&lt;p&gt;I&amp;#39;d say the important thing is to start with a simple project that you think is achievable and builds largely on what you already know (if anything). If you start too big it can be overwhelming trying to connect all of the pieces, and you might not end up finishing at all.&lt;\/p&gt;\n&lt;\/div&gt;",
          "quarantine": false,
          "subreddit": "androiddev",
          "score_hidden": false,
          "name": "t1_d0via5p",
          "created": 1457690407,
          "author_flair_text": null,
          "link_url": "https:\/\/www.reddit.com\/r\/androiddev\/comments\/49wfsl\/with_no_job_and_no_school_how_fast_could_you\/",
          "created_utc": 1457661607,
          "ups": 1,
          "mod_reports": [

          ],
          "num_reports": null,
          "distinguished": null
        }
      },
      {
        "kind": "t1",
        "data": {
          "subreddit_id": "t5_2zbq7",
          "link_title": "Fox News Almost Hosted a Trump\/Sanders Debate, But Trump Backed Out",
          "banned_by": null,
          "removal_reason": null,
          "link_id": "t3_49l5ql",
          "link_author": "heho100",
          "likes": true,
          "replies": "",
          "user_reports": [

          ],
          "saved": false,
          "id": "d0sva72",
          "gilded": 0,
          "archived": false,
          "stickied": false,
          "author": "damien5314",
          "parent_id": "t1_d0su7xg",
          "score": 14,
          "approved_by": null,
          "over_18": false,
          "report_reasons": null,
          "controversiality": 0,
          "body": "heh, that's actually a pretty good reference. too bad s\/he backed out of it like a pansy.",
          "edited": false,
          "author_flair_css_class": null,
          "downs": 0,
          "body_html": "&lt;div class=\"md\"&gt;&lt;p&gt;heh, that&amp;#39;s actually a pretty good reference. too bad s\/he backed out of it like a pansy.&lt;\/p&gt;\n&lt;\/div&gt;",
          "quarantine": false,
          "subreddit": "SandersForPresident",
          "score_hidden": false,
          "name": "t1_d0sva72",
          "created": 1457518889,
          "author_flair_text": null,
          "link_url": "http:\/\/www.mediaite.com\/tv\/fox-news-almost-hosted-a-trumpsanders-debate-but-trump-backed-out\/",
          "created_utc": 1457490089,
          "ups": 14,
          "mod_reports": [

          ],
          "num_reports": null,
          "distinguished": null
        }
      },
      {
        "kind": "t1",
        "data": {
          "subreddit_id": "t5_2qizd",
          "link_title": "Refresh token question",
          "banned_by": null,
          "removal_reason": null,
          "link_id": "t3_49jy3b",
          "link_author": "ogerkoenig",
          "likes": true,
          "replies": "",
          "user_reports": [

          ],
          "saved": false,
          "id": "d0sg179",
          "gilded": 0,
          "archived": false,
          "stickied": false,
          "author": "damien5314",
          "parent_id": "t3_49jy3b",
          "score": 3,
          "approved_by": null,
          "over_18": false,
          "report_reasons": null,
          "controversiality": 0,
          "body": "Yes, from my experiences you don't actually get a new refresh token when you refresh your authentication, so you definitely have to save and use the original.",
          "edited": false,
          "author_flair_css_class": null,
          "downs": 0,
          "body_html": "&lt;div class=\"md\"&gt;&lt;p&gt;Yes, from my experiences you don&amp;#39;t actually get a new refresh token when you refresh your authentication, so you definitely have to save and use the original.&lt;\/p&gt;\n&lt;\/div&gt;",
          "quarantine": false,
          "subreddit": "redditdev",
          "score_hidden": false,
          "name": "t1_d0sg179",
          "created": 1457496723,
          "author_flair_text": null,
          "link_url": "https:\/\/www.reddit.com\/r\/redditdev\/comments\/49jy3b\/refresh_token_question\/",
          "created_utc": 1457467923,
          "ups": 3,
          "mod_reports": [

          ],
          "num_reports": null,
          "distinguished": null
        }
      },
      {
        "kind": "t1",
        "data": {
          "subreddit_id": "t5_2qwj8",
          "link_title": "Anyone using Project Rider EAP?",
          "banned_by": null,
          "removal_reason": null,
          "link_id": "t3_48ipfz",
          "link_author": "aportner",
          "likes": true,
          "replies": "",
          "user_reports": [

          ],
          "saved": false,
          "id": "d0mq4kj",
          "gilded": 0,
          "archived": false,
          "stickied": false,
          "author": "damien5314",
          "parent_id": "t1_d0k4r6i",
          "score": 1,
          "approved_by": null,
          "over_18": false,
          "report_reasons": null,
          "controversiality": 0,
          "body": "If you figure out how to get the preprocessor directives to be recognized, please share. Right now I'm having to comment directives to get the code to compile temporarily, then remember to uncomment before I build, which isn't too elegant.\n\nI'm going to try to figure it out myself but I'm fairly new to Unity\/C# dev so I'm not sure how far I'm going to get.",
          "edited": false,
          "author_flair_css_class": null,
          "downs": 0,
          "body_html": "&lt;div class=\"md\"&gt;&lt;p&gt;If you figure out how to get the preprocessor directives to be recognized, please share. Right now I&amp;#39;m having to comment directives to get the code to compile temporarily, then remember to uncomment before I build, which isn&amp;#39;t too elegant.&lt;\/p&gt;\n\n&lt;p&gt;I&amp;#39;m going to try to figure it out myself but I&amp;#39;m fairly new to Unity\/C# dev so I&amp;#39;m not sure how far I&amp;#39;m going to get.&lt;\/p&gt;\n&lt;\/div&gt;",
          "quarantine": false,
          "subreddit": "Unity3D",
          "score_hidden": false,
          "name": "t1_d0mq4kj",
          "created": 1457080213,
          "author_flair_text": null,
          "link_url": "https:\/\/www.reddit.com\/r\/Unity3D\/comments\/48ipfz\/anyone_using_project_rider_eap\/",
          "created_utc": 1457051413,
          "ups": 1,
          "mod_reports": [

          ],
          "num_reports": null,
          "distinguished": null
        }
      },
      {
        "kind": "t1",
        "data": {
          "subreddit_id": "t5_30cz1",
          "link_title": "PSA: Calling your teammates shit will make them play like shit",
          "banned_by": null,
          "removal_reason": null,
          "link_id": "t3_47pnzt",
          "link_author": "Maynes_",
          "likes": true,
          "replies": "",
          "user_reports": [

          ],
          "saved": false,
          "id": "d0fgnqh",
          "gilded": 0,
          "archived": false,
          "stickied": false,
          "author": "damien5314",
          "parent_id": "t1_d0fdlxd",
          "score": 1,
          "approved_by": null,
          "over_18": false,
          "report_reasons": null,
          "controversiality": 0,
          "body": "I really wish there was a way to auto-veto forfeit votes, though. I already know the match isn't going very well, I don't need my teammates voting to increase my anxiety. In my 1300 games played I've never voted to forfeit, anyway.",
          "edited": false,
          "author_flair_css_class": "steam",
          "downs": 0,
          "body_html": "&lt;div class=\"md\"&gt;&lt;p&gt;I really wish there was a way to auto-veto forfeit votes, though. I already know the match isn&amp;#39;t going very well, I don&amp;#39;t need my teammates voting to increase my anxiety. In my 1300 games played I&amp;#39;ve never voted to forfeit, anyway.&lt;\/p&gt;\n&lt;\/div&gt;",
          "quarantine": false,
          "subreddit": "RocketLeague",
          "score_hidden": false,
          "name": "t1_d0fgnqh",
          "created": 1456574078,
          "author_flair_text": "healingvision02",
          "link_url": "https:\/\/www.reddit.com\/r\/RocketLeague\/comments\/47pnzt\/psa_calling_your_teammates_shit_will_make_them\/",
          "created_utc": 1456545278,
          "ups": 1,
          "mod_reports": [

          ],
          "num_reports": null,
          "distinguished": null
        }
      },
      {
        "kind": "t1",
        "data": {
          "subreddit_id": "t5_2s7tt",
          "link_title": "I was 7 years old.",
          "banned_by": null,
          "removal_reason": null,
          "link_id": "t3_47eicq",
          "link_author": "sansiben",
          "likes": true,
          "replies": "",
          "user_reports": [

          ],
          "saved": false,
          "id": "d0cr9bo",
          "gilded": 0,
          "archived": false,
          "stickied": false,
          "author": "damien5314",
          "parent_id": "t1_d0ce7kh",
          "score": 2,
          "approved_by": null,
          "over_18": false,
          "report_reasons": null,
          "controversiality": 0,
          "body": "This always bugged me about Jews until I found out about the concept of an [ethnoreligious group](https:\/\/en.m.wikipedia.org\/wiki\/Ethnoreligious). Could never understand why they aren't just white people.",
          "edited": false,
          "author_flair_css_class": null,
          "downs": 0,
          "body_html": "&lt;div class=\"md\"&gt;&lt;p&gt;This always bugged me about Jews until I found out about the concept of an &lt;a href=\"https:\/\/en.m.wikipedia.org\/wiki\/Ethnoreligious\"&gt;ethnoreligious group&lt;\/a&gt;. Could never understand why they aren&amp;#39;t just white people.&lt;\/p&gt;\n&lt;\/div&gt;",
          "quarantine": false,
          "subreddit": "AdviceAnimals",
          "score_hidden": false,
          "name": "t1_d0cr9bo",
          "created": 1456394443,
          "author_flair_text": null,
          "link_url": "http:\/\/imgur.com\/IJK7jdC",
          "created_utc": 1456365643,
          "ups": 2,
          "mod_reports": [

          ],
          "num_reports": null,
          "distinguished": null
        }
      },
      {
        "kind": "t1",
        "data": {
          "subreddit_id": "t5_36w64",
          "link_title": "deleting this account",
          "banned_by": null,
          "removal_reason": null,
          "link_id": "t3_4648v3",
          "link_author": "[deleted]",
          "likes": true,
          "replies": "",
          "user_reports": [

          ],
          "saved": false,
          "id": "d029okh",
          "gilded": 0,
          "archived": false,
          "stickied": false,
          "author": "damien5314",
          "parent_id": "t3_4648v3",
          "score": 1,
          "approved_by": null,
          "over_18": false,
          "report_reasons": [

          ],
          "controversiality": 0,
          "body": "commenting as subreddit moderator",
          "edited": false,
          "author_flair_css_class": null,
          "downs": 0,
          "body_html": "&lt;div class=\"md\"&gt;&lt;p&gt;commenting as subreddit moderator&lt;\/p&gt;\n&lt;\/div&gt;",
          "quarantine": false,
          "subreddit": "damien5314apitest",
          "score_hidden": false,
          "name": "t1_d029okh",
          "created": 1455681301,
          "author_flair_text": null,
          "link_url": "https:\/\/www.reddit.com\/r\/damien5314apitest\/comments\/4648v3\/deleting_this_account\/",
          "created_utc": 1455652501,
          "ups": 1,
          "mod_reports": [

          ],
          "num_reports": 0,
          "distinguished": null
        }
      },
      {
        "kind": "t1",
        "data": {
          "subreddit_id": "t5_30cz1",
          "link_title": "Players are deleting the Wasteland map from game files to avoid playing it in ranked. Is this bannable?",
          "banned_by": null,
          "removal_reason": null,
          "link_id": "t3_45bp6g",
          "link_author": "RyanGUK",
          "likes": true,
          "replies": "",
          "user_reports": [

          ],
          "saved": false,
          "id": "czxyqr1",
          "gilded": 0,
          "archived": false,
          "stickied": false,
          "author": "damien5314",
          "parent_id": "t1_czxtu1q",
          "score": 3,
          "approved_by": null,
          "over_18": false,
          "report_reasons": null,
          "controversiality": 0,
          "body": "Hmm, I wouldn't bet on you being okay there. They might start off by simply checking if the required files are present, but if hackers end up working around that (and they will) the devs might end up taking a hash of the full assets to ensure nothing was tampered with. I'm not with Psyonix or anything, that's just how I could see the cheater check working.\n\nThat said, the patch notes _did_ mention some optimizations made for Wastelands with respect to game performance, hopefully that helps you on that map, at least.",
          "edited": false,
          "author_flair_css_class": "steam",
          "downs": 0,
          "body_html": "&lt;div class=\"md\"&gt;&lt;p&gt;Hmm, I wouldn&amp;#39;t bet on you being okay there. They might start off by simply checking if the required files are present, but if hackers end up working around that (and they will) the devs might end up taking a hash of the full assets to ensure nothing was tampered with. I&amp;#39;m not with Psyonix or anything, that&amp;#39;s just how I could see the cheater check working.&lt;\/p&gt;\n\n&lt;p&gt;That said, the patch notes &lt;em&gt;did&lt;\/em&gt; mention some optimizations made for Wastelands with respect to game performance, hopefully that helps you on that map, at least.&lt;\/p&gt;\n&lt;\/div&gt;",
          "quarantine": false,
          "subreddit": "RocketLeague",
          "score_hidden": false,
          "name": "t1_czxyqr1",
          "created": 1455351918,
          "author_flair_text": "healingvision02",
          "link_url": "http:\/\/reddit.com\/r\/RocketLeague\/comments\/459ftp\/kronovi_showed_more_emotion_after_a_goal_on\/czwah2i",
          "created_utc": 1455323118,
          "ups": 3,
          "mod_reports": [

          ],
          "num_reports": null,
          "distinguished": null
        }
      },
      {
        "kind": "t1",
        "data": {
          "subreddit_id": "t5_2r26y",
          "link_title": "Recommended practices to load data into extended (custom) views",
          "banned_by": null,
          "removal_reason": null,
          "link_id": "t3_459dpw",
          "link_author": "ZakTaccardi",
          "likes": true,
          "replies": "",
          "user_reports": [

          ],
          "saved": false,
          "id": "czwr3n0",
          "gilded": 0,
          "archived": false,
          "stickied": false,
          "author": "damien5314",
          "parent_id": "t3_459dpw",
          "score": 1,
          "approved_by": null,
          "over_18": false,
          "report_reasons": null,
          "controversiality": 0,
          "body": "I think I do it similar to #2, but with presenters. My fragments implement a View interface and construct a presenter in onCreate. My presenters extend from a base interface that has lifecycle callbacks, which I forward from the matching callback in my fragment, so I can react to the lifecycle changes appropriately.",
          "edited": false,
          "author_flair_css_class": null,
          "downs": 0,
          "body_html": "&lt;div class=\"md\"&gt;&lt;p&gt;I think I do it similar to #2, but with presenters. My fragments implement a View interface and construct a presenter in onCreate. My presenters extend from a base interface that has lifecycle callbacks, which I forward from the matching callback in my fragment, so I can react to the lifecycle changes appropriately.&lt;\/p&gt;\n&lt;\/div&gt;",
          "quarantine": false,
          "subreddit": "androiddev",
          "score_hidden": false,
          "name": "t1_czwr3n0",
          "created": 1455268606,
          "author_flair_text": null,
          "link_url": "https:\/\/www.reddit.com\/r\/androiddev\/comments\/459dpw\/recommended_practices_to_load_data_into_extended\/",
          "created_utc": 1455239806,
          "ups": 1,
          "mod_reports": [

          ],
          "num_reports": null,
          "distinguished": null
        }
      },
      {
        "kind": "t1",
        "data": {
          "subreddit_id": "t5_2qh1i",
          "link_title": "What is one \"unwritten rule\" you think everyone should know and follow?",
          "banned_by": null,
          "removal_reason": null,
          "link_id": "t3_454e8h",
          "link_author": "Ovenproofcorgi",
          "likes": true,
          "replies": "",
          "user_reports": [

          ],
          "saved": false,
          "id": "czvf2yr",
          "gilded": 0,
          "archived": false,
          "stickied": false,
          "author": "damien5314",
          "parent_id": "t1_czv4gbh",
          "score": 1,
          "approved_by": null,
          "over_18": false,
          "report_reasons": null,
          "controversiality": 0,
          "body": "It's really on the person holding the door to make the judgment call. If they have to hold it for a few seconds before I get there and it bothers them, they shouldn't have held the door in the first place.",
          "edited": false,
          "author_flair_css_class": null,
          "downs": 0,
          "body_html": "&lt;div class=\"md\"&gt;&lt;p&gt;It&amp;#39;s really on the person holding the door to make the judgment call. If they have to hold it for a few seconds before I get there and it bothers them, they shouldn&amp;#39;t have held the door in the first place.&lt;\/p&gt;\n&lt;\/div&gt;",
          "quarantine": false,
          "subreddit": "AskReddit",
          "score_hidden": false,
          "name": "t1_czvf2yr",
          "created": 1455178168,
          "author_flair_text": null,
          "link_url": "https:\/\/www.reddit.com\/r\/AskReddit\/comments\/454e8h\/what_is_one_unwritten_rule_you_think_everyone\/",
          "created_utc": 1455149368,
          "ups": 1,
          "mod_reports": [

          ],
          "num_reports": null,
          "distinguished": null
        }
      },
      {
        "kind": "t1",
        "data": {
          "subreddit_id": "t5_2qh3u",
          "link_title": "Ask A San Francisco Native: Is Saving Parking Spaces By Standing In Them Kosher In The 415?: SFist",
          "banned_by": null,
          "removal_reason": null,
          "link_id": "t3_4547t3",
          "link_author": "calaesthetic",
          "likes": true,
          "replies": "",
          "user_reports": [

          ],
          "saved": false,
          "id": "czv56fg",
          "gilded": 0,
          "archived": false,
          "stickied": false,
          "author": "damien5314",
          "parent_id": "t3_4547t3",
          "score": 9,
          "approved_by": null,
          "over_18": false,
          "report_reasons": null,
          "controversiality": 0,
          "body": "&gt; Those who did admit to doing it did so with a bit of embarrassment, conceding that it is a pretty shitty thing to do. They also wanted to assure me that if someone drove up wanting the spot before their friend got there, that they'd totally relinquish it.\n\nSo why try to claim the spot early in the first place? Just hoping everyone who drives by is enough of a pushover to ignore the empty space with a person standing in it? :(",
          "edited": false,
          "author_flair_css_class": null,
          "downs": 0,
          "body_html": "&lt;div class=\"md\"&gt;&lt;blockquote&gt;\n&lt;p&gt;Those who did admit to doing it did so with a bit of embarrassment, conceding that it is a pretty shitty thing to do. They also wanted to assure me that if someone drove up wanting the spot before their friend got there, that they&amp;#39;d totally relinquish it.&lt;\/p&gt;\n&lt;\/blockquote&gt;\n\n&lt;p&gt;So why try to claim the spot early in the first place? Just hoping everyone who drives by is enough of a pushover to ignore the empty space with a person standing in it? :(&lt;\/p&gt;\n&lt;\/div&gt;",
          "quarantine": false,
          "subreddit": "sanfrancisco",
          "score_hidden": false,
          "name": "t1_czv56fg",
          "created": 1455163802,
          "author_flair_text": null,
          "link_url": "http:\/\/sfist.com\/2016\/02\/10\/415_or_just_jerk.php",
          "created_utc": 1455135002,
          "ups": 9,
          "mod_reports": [

          ],
          "num_reports": null,
          "distinguished": null
        }
      },
      {
        "kind": "t1",
        "data": {
          "subreddit_id": "t5_30cz1",
          "link_title": "Ask Dumb Questions + Newbies Welcoming Wednesday \u2665 (2016.02.10)",
          "banned_by": null,
          "removal_reason": null,
          "link_id": "t3_4513hf",
          "link_author": "AutoModerator",
          "likes": true,
          "replies": "",
          "user_reports": [

          ],
          "saved": false,
          "id": "czv4gw2",
          "gilded": 0,
          "archived": false,
          "stickied": false,
          "author": "damien5314",
          "parent_id": "t1_czuynzp",
          "score": 1,
          "approved_by": null,
          "over_18": false,
          "report_reasons": null,
          "controversiality": 0,
          "body": "I always wondered about Solo Standard, too. No matter what time I log on, the queue indicator makes it seem like there's around 3-5x more players in the normal Standard queue than Solo. I guess a lot of people play with friends.",
          "edited": false,
          "author_flair_css_class": "steam",
          "downs": 0,
          "body_html": "&lt;div class=\"md\"&gt;&lt;p&gt;I always wondered about Solo Standard, too. No matter what time I log on, the queue indicator makes it seem like there&amp;#39;s around 3-5x more players in the normal Standard queue than Solo. I guess a lot of people play with friends.&lt;\/p&gt;\n&lt;\/div&gt;",
          "quarantine": false,
          "subreddit": "RocketLeague",
          "score_hidden": false,
          "name": "t1_czv4gw2",
          "created": 1455162828,
          "author_flair_text": "healingvision02",
          "link_url": "https:\/\/www.reddit.com\/r\/RocketLeague\/comments\/4513hf\/ask_dumb_questions_newbies_welcoming_wednesday\/",
          "created_utc": 1455134028,
          "ups": 1,
          "mod_reports": [

          ],
          "num_reports": null,
          "distinguished": null
        }
      },
      {
        "kind": "t1",
        "data": {
          "subreddit_id": "t5_2sgq6",
          "link_title": "Games with great mechanics that keep you coming back.",
          "banned_by": null,
          "removal_reason": null,
          "link_id": "t3_44ewh5",
          "link_author": "gr00vymeat",
          "likes": true,
          "replies": "",
          "user_reports": [

          ],
          "saved": false,
          "id": "czpz60q",
          "gilded": 0,
          "archived": false,
          "stickied": false,
          "author": "damien5314",
          "parent_id": "t3_44ewh5",
          "score": 2,
          "approved_by": null,
          "over_18": false,
          "report_reasons": null,
          "controversiality": 0,
          "body": "I've been playing music rhythm games, particularly DDR\/In the Groove, since 2003. Being around the community for so long, it seems like people who are really into the genre play it for life.",
          "edited": false,
          "author_flair_css_class": null,
          "downs": 0,
          "body_html": "&lt;div class=\"md\"&gt;&lt;p&gt;I&amp;#39;ve been playing music rhythm games, particularly DDR\/In the Groove, since 2003. Being around the community for so long, it seems like people who are really into the genre play it for life.&lt;\/p&gt;\n&lt;\/div&gt;",
          "quarantine": false,
          "subreddit": "truegaming",
          "score_hidden": false,
          "name": "t1_czpz60q",
          "created": 1454797096,
          "author_flair_text": null,
          "link_url": "https:\/\/www.reddit.com\/r\/truegaming\/comments\/44ewh5\/games_with_great_mechanics_that_keep_you_coming\/",
          "created_utc": 1454768296,
          "ups": 2,
          "mod_reports": [

          ],
          "num_reports": null,
          "distinguished": null
        }
      },
      {
        "kind": "t1",
        "data": {
          "subreddit_id": "t5_2zbq7",
          "link_title": "Bernie Sanders on Twitter: \"Most progressives that I know don't raise millions of dollars from Wall Street.\"",
          "banned_by": null,
          "removal_reason": null,
          "link_id": "t3_441g7a",
          "link_author": "codyboughman",
          "likes": true,
          "replies": "",
          "user_reports": [

          ],
          "saved": false,
          "id": "czn4936",
          "gilded": 0,
          "archived": false,
          "stickied": false,
          "author": "damien5314",
          "parent_id": "t1_czmxs72",
          "score": 0,
          "approved_by": null,
          "over_18": false,
          "report_reasons": null,
          "controversiality": 0,
          "body": "If you already have authenticated cookies in your browser from your ISP, perhaps they don't show you a prompt to sign in.",
          "edited": false,
          "author_flair_css_class": null,
          "downs": 0,
          "body_html": "&lt;div class=\"md\"&gt;&lt;p&gt;If you already have authenticated cookies in your browser from your ISP, perhaps they don&amp;#39;t show you a prompt to sign in.&lt;\/p&gt;\n&lt;\/div&gt;",
          "quarantine": false,
          "subreddit": "SandersForPresident",
          "score_hidden": false,
          "name": "t1_czn4936",
          "created": 1454583314,
          "author_flair_text": null,
          "link_url": "https:\/\/twitter.com\/BernieSanders\/status\/694967503995457536",
          "created_utc": 1454554514,
          "ups": 0,
          "mod_reports": [

          ],
          "num_reports": null,
          "distinguished": null
        }
      },
      {
        "kind": "t1",
        "data": {
          "subreddit_id": "t5_36w64",
          "link_title": "1200 x 600",
          "banned_by": null,
          "removal_reason": null,
          "link_id": "t3_40hx2m",
          "link_author": "simpleredditreader",
          "likes": true,
          "replies": "",
          "user_reports": [

          ],
          "saved": false,
          "id": "cz5xbvs",
          "gilded": 0,
          "archived": false,
          "stickied": false,
          "author": "damien5314",
          "parent_id": "t3_40hx2m",
          "score": 1,
          "approved_by": null,
          "over_18": false,
          "report_reasons": [

          ],
          "controversiality": 0,
          "body": "testing2",
          "edited": false,
          "author_flair_css_class": null,
          "downs": 0,
          "body_html": "&lt;div class=\"md\"&gt;&lt;p&gt;testing2&lt;\/p&gt;\n&lt;\/div&gt;",
          "quarantine": false,
          "subreddit": "damien5314apitest",
          "score_hidden": false,
          "name": "t1_cz5xbvs",
          "created": 1453366380,
          "author_flair_text": null,
          "link_url": "http:\/\/imgur.com\/LobmzC1",
          "created_utc": 1453337580,
          "ups": 1,
          "mod_reports": [

          ],
          "num_reports": 0,
          "distinguished": null
        }
      },
      {
        "kind": "t1",
        "data": {
          "subreddit_id": "t5_36w64",
          "link_title": "1200 x 600",
          "banned_by": null,
          "removal_reason": null,
          "link_id": "t3_40hx2m",
          "link_author": "simpleredditreader",
          "likes": true,
          "replies": "",
          "user_reports": [

          ],
          "saved": false,
          "id": "cz5xafr",
          "gilded": 0,
          "archived": false,
          "stickied": false,
          "author": "damien5314",
          "parent_id": "t3_40hx2m",
          "score": 1,
          "approved_by": null,
          "over_18": false,
          "report_reasons": [

          ],
          "controversiality": 0,
          "body": "testing",
          "edited": false,
          "author_flair_css_class": null,
          "downs": 0,
          "body_html": "&lt;div class=\"md\"&gt;&lt;p&gt;testing&lt;\/p&gt;\n&lt;\/div&gt;",
          "quarantine": false,
          "subreddit": "damien5314apitest",
          "score_hidden": false,
          "name": "t1_cz5xafr",
          "created": 1453366316,
          "author_flair_text": null,
          "link_url": "http:\/\/imgur.com\/LobmzC1",
          "created_utc": 1453337516,
          "ups": 1,
          "mod_reports": [

          ],
          "num_reports": 0,
          "distinguished": null
        }
      },
      {
        "kind": "t1",
        "data": {
          "subreddit_id": "t5_2qh3u",
          "link_title": "Spotted in the Mission",
          "banned_by": null,
          "removal_reason": null,
          "link_id": "t3_41565z",
          "link_author": "Arro",
          "likes": true,
          "replies": "",
          "user_reports": [

          ],
          "saved": false,
          "id": "cyzyj9m",
          "gilded": 0,
          "archived": false,
          "stickied": false,
          "author": "damien5314",
          "parent_id": "t3_41565z",
          "score": 13,
          "approved_by": null,
          "over_18": false,
          "report_reasons": null,
          "controversiality": 0,
          "body": "Usually when I see wanted posters with someone's face on it, I think, \"eh I probably wouldn't recognize that person even if I actually ran into them.\" I think in this case, I actually would. ",
          "edited": false,
          "author_flair_css_class": null,
          "downs": 0,
          "body_html": "&lt;div class=\"md\"&gt;&lt;p&gt;Usually when I see wanted posters with someone&amp;#39;s face on it, I think, &amp;quot;eh I probably wouldn&amp;#39;t recognize that person even if I actually ran into them.&amp;quot; I think in this case, I actually would. &lt;\/p&gt;\n&lt;\/div&gt;",
          "quarantine": false,
          "subreddit": "sanfrancisco",
          "score_hidden": false,
          "name": "t1_cyzyj9m",
          "created": 1452938262,
          "author_flair_text": null,
          "link_url": "http:\/\/i.imgur.com\/WnccPe6.jpg",
          "created_utc": 1452909462,
          "ups": 13,
          "mod_reports": [

          ],
          "num_reports": null,
          "distinguished": null
        }
      },
      {
        "kind": "t1",
        "data": {
          "subreddit_id": "t5_2qh0u",
          "link_title": "Reality of divorce. Found in my 7 year old daughters school bag.",
          "banned_by": null,
          "removal_reason": null,
          "link_id": "t3_414mre",
          "link_author": "dfGobBluth",
          "likes": true,
          "replies": "",
          "user_reports": [

          ],
          "saved": false,
          "id": "cyzvheb",
          "gilded": 0,
          "archived": false,
          "stickied": false,
          "author": "damien5314",
          "parent_id": "t1_cyzqix4",
          "score": 1,
          "approved_by": null,
          "over_18": false,
          "report_reasons": null,
          "controversiality": 0,
          "body": "I think I lucked out. My parents separated when I was around 6, but my sister (3) and I were not involved in the custody battle whatsoever. We never saw a court room, my parents wouldn't allow it. I don't know how much impact it had on our psychology behind the scenes, but honestly I've never had any resentment toward them for separating, or wished they were still together or anything like that.",
          "edited": false,
          "author_flair_css_class": null,
          "downs": 0,
          "body_html": "&lt;div class=\"md\"&gt;&lt;p&gt;I think I lucked out. My parents separated when I was around 6, but my sister (3) and I were not involved in the custody battle whatsoever. We never saw a court room, my parents wouldn&amp;#39;t allow it. I don&amp;#39;t know how much impact it had on our psychology behind the scenes, but honestly I&amp;#39;ve never had any resentment toward them for separating, or wished they were still together or anything like that.&lt;\/p&gt;\n&lt;\/div&gt;",
          "quarantine": false,
          "subreddit": "pics",
          "score_hidden": false,
          "name": "t1_cyzvheb",
          "created": 1452932852,
          "author_flair_text": null,
          "link_url": "http:\/\/imgur.com\/1WJlw0I.jpg",
          "created_utc": 1452904052,
          "ups": 1,
          "mod_reports": [

          ],
          "num_reports": null,
          "distinguished": null
        }
      }
    ],
    "after": "t1_cyzvheb",
    "before": null
  }
}